unisonai/__init__.py
unisonai/agent.py
unisonai/async_helper.py
unisonai/clan.py
unisonai/config/__init__.py
unisonai/config/config.py
unisonai/llms/Basellm.py
unisonai/llms/__init__.py
unisonai/llms/anthropicllm.py
unisonai/llms/cerebras.py
unisonai/llms/coherellm.py
unisonai/llms/genai.py
unisonai/llms/groqllm.py
unisonai/llms/mixtral.py
unisonai/llms/openaillm.py
unisonai/llms/xai.py
unisonai/prompts/__init__.py
unisonai/prompts/agent.py
unisonai/prompts/individual.py
unisonai/prompts/manager.py
unisonai/prompts/plan.py
unisonai/tools/__init__.py
unisonai/tools/memory.py
unisonai/tools/rag.py
unisonai/tools/tool.py
unisonai/tools/types.py
unisonai-1.2.dist-info/LICENSE
unisonai-1.2.dist-info/METADATA
unisonai-1.2.dist-info/WHEEL
unisonai-1.2.dist-info/top_level.txt
unisonai-1.2.dist-info/RECORD
