Metadata-Version: 2.1
Name: unisonai
Version: 1.2
Summary: UnisonAI Multi-Agent Framework provides a flexible, light-weight experience and extensible environment for creating and coordinating multiple AI agents.
Author: E5Anant (Anant Sharma)
Author-email: e5anant2011@gmail.com
Keywords: agents,unisonai,unisonAI,multi-agent,clan,python,light-weight,agent-framework,framework,ai,ai tools,ai agents,llms,open-source,a2a,agent to agent
Classifier: Development Status :: 4 - Beta
Classifier: Intended Audience :: Developers
Classifier: Programming Language :: Python :: 3
Classifier: Operating System :: Unix
Classifier: Operating System :: MacOS :: MacOS X
Classifier: Operating System :: Microsoft :: Windows
License-File: LICENSE
Requires-Dist: cohere
Requires-Dist: groq
Requires-Dist: rich
Requires-Dist: python-dotenv
Requires-Dist: google-generativeai
Requires-Dist: requests
Requires-Dist: colorama
Requires-Dist: anthropic
Requires-Dist: openai>=1.13.3
Requires-Dist: mistralai
Requires-Dist: pydantic>=2.4.2
Requires-Dist: nest-asyncio
Requires-Dist: cerebras
